MANIFEST.in
README.md
pyproject.toml
setup.cfg
setup.py
version.txt
mintregrid.egg-info/PKG-INFO
mintregrid.egg-info/SOURCES.txt
mintregrid.egg-info/dependency_links.txt
mintregrid.egg-info/requires.txt
mintregrid.egg-info/top_level.txt
pymint/__init__.py
pymint/__init__.py.in
pymint/grid.py
pymint/polyline_integral.py
pymint/regrid_edges.py
src/CmdLineArgParser.cpp
src/CmdLineArgParser.h
src/GrExprAdaptor.cpp
src/GrExprAdaptor.h
src/GrExprParser.cpp
src/GrExprParser.h
src/MvFunctors.h
src/MvMat_double.cpp
src/MvMatrix.h
src/MvVector.cpp
src/MvVector.h
src/mntCellLocator.cpp
src/mntCellLocator.h
src/mntCmdLineArgParser.cpp
src/mntCmdLineArgParser.h
src/mntDots.cpp
src/mntDots.h
src/mntGrid.cpp
src/mntGrid.h
src/mntLatLon.cpp
src/mntLatLon.h
src/mntLineLineIntersector.h
src/mntLineTriangleIntersector.cpp
src/mntLineTriangleIntersector.h
src/mntMatMxN.cpp
src/mntMatMxN.h
src/mntMultiArrayIter.cpp
src/mntMultiArrayIter.h
src/mntNcAttributes.cpp
src/mntNcAttributes.h
src/mntNcDimensions.cpp
src/mntNcDimensions.h
src/mntNcFieldRead.cpp
src/mntNcFieldRead.h
src/mntNcFieldWrite.cpp
src/mntNcFieldWrite.h
src/mntPolylineIntegral.cpp
src/mntPolylineIntegral.h
src/mntPolylineParser.cpp
src/mntPolylineParser.h
src/mntPolysegmentIter.cpp
src/mntPolysegmentIter.h
src/mntQuadEdgeIter.cpp
src/mntQuadEdgeIter.h
src/mntRegridAxis.cpp
src/mntRegridAxis.h
src/mntRegridEdges.cpp
src/mntRegridEdges.h
src/mntUgrid2D.cpp
src/mntUgrid2D.h
src/mntVecN.cpp
src/mntVecN.h
src/mntWeights.cpp
src/mntWeights.h
src/vmtCellLocator.cpp
src/vmtCellLocator.h