Metadata-Version: 2.1
Name: mintregrid
Version: 1.7.10
Summary: Mimetic INterpolation on the sphere
Home-page: https://github.com/pletzer/mint
Author: Alexander Pletzer
Author-email: alexander.pletzer@nesi.org.nz
License: UNKNOWN
Platform: UNKNOWN
Classifier: Programming Language :: Python :: 3
